comments/__init__.py
comments/admin.py
comments/forms.py
comments/models.py
comments/tests.py
comments/urls.py
comments/views.py
comments/migrations/0001_initial.py
comments/migrations/__init__.py
comments/static/js/comments.js
comments/static/js/jquery.js
comments/templates/comments/base_comment.html
comments/templates/comments/comment.html
comments/templates/comments/comment_edit_form.html
comments/templates/comments/comment_form.html
comments/templates/comments/comments.html
comments/templates/comments/jQuery.html
comments/templatetags/__init__.py
comments/templatetags/comments_tags.py
django_ajax_comments-1.1.0.dev1.dist-info/DESCRIPTION.rst
django_ajax_comments-1.1.0.dev1.dist-info/METADATA
django_ajax_comments-1.1.0.dev1.dist-info/RECORD
django_ajax_comments-1.1.0.dev1.dist-info/WHEEL
django_ajax_comments-1.1.0.dev1.dist-info/metadata.json
django_ajax_comments-1.1.0.dev1.dist-info/top_level.txt
test_app/__init__.py
test_app/settings.py
test_app/urls.py
