Metadata-Version: 2.0
Name: django-ajax-comments
Version: 1.1.0.dev1
Summary: Associates comments functionality with any given model
Home-page: https://github.com/dreidev/Comments
Author: DREIDEV
Author-email: info@dreidev.com
License: MIT
Keywords: comments comment development
Platform: UNKNOWN
Classifier: Development Status :: 3 - Alpha
Classifier: Intended Audience :: Developers
Classifier: Topic :: Software Development :: Build Tools
Classifier: License :: OSI Approved :: MIT License
Classifier: Programming Language :: Python :: 2
Classifier: Programming Language :: Python :: 2.6
Classifier: Programming Language :: Python :: 2.7
Classifier: Programming Language :: Python :: 3
Classifier: Programming Language :: Python :: 3.2
Classifier: Programming Language :: Python :: 3.3
Classifier: Programming Language :: Python :: 3.4
